<?xml version="1.0" encoding="utf-8"?><Dokument xmlns:ns0="http://FT.PIP.Afskrift.Schemas"><MetaMeeting tingdokID="1901548"><ParliamentarySession tingdokID="200052">20211</ParliamentarySession><ParliamentaryGroup tingdokID="528058">Folketinget</ParliamentaryGroup><MeetingNumber>126</MeetingNumber><DateOfSitting>2022-09-08T09:00:00</DateOfSitting><Location>Folketingssalen</Location><EdixiDocLocation>W:\20211\M126\</EdixiDocLocation><AudioFileFolder>X:\Arbor\FT2021\126\SALEN\</AudioFileFolder></MetaMeeting><TitelGruppe><Titel><Linea><Char>126. møde</Char></Linea></Titel><UnderTitel><Linea><Char>Torsdag den 8. september 2022 kl. 9.00</Char></Linea></UnderTitel></TitelGruppe><DagsordenPlan><Rubrica><Linea><Char>Dagsorden</Char></Linea></Rubrica><PunktTekst><Exitus><Linea><Char formaChar="Bold">1) 2. behandling af lovforslag nr. L 204:</Char></Linea></Exitus><Exitus><Linea><Char>Forslag til lov om ændring af lov om afgift af elektricitet og ligningsloven. (Nedsættelse af den almindelige elafgift i fjerde kvartal 2022 og i 2023 og forhøjelse af det maksimale beskæftigelsesfradrag for indkomstårene 2022 og 2023).</Char></Linea></Exitus><Exitus><Linea><Char>Af skatteministeren (Jeppe Bruus).</Char></Linea></Exitus><Exitus><Linea><Char>(Fremsættelse 23.08.2022. 1. behandling 25.08.2022. Betænkning 01.09.2022).</Char></Linea></Exitus></PunktTekst><PunktTekst><Exitus><Linea><Char formaChar="Bold">2) 2. behandling af lovforslag nr. L 205:</Char></Linea></Exitus><Exitus><Linea><Char>Forslag til lov om ændring af lov om ændring af SU-loven. (Fremrykning af forhøjelse af SU-fribeløb).</Char></Linea></Exitus><Exitus><Linea><Char>Af uddannelses- og forskningsministeren (Jesper Petersen).</Char></Linea></Exitus><Exitus><Linea><Char>(Fremsættelse 23.08.2022. 1. behandling 25.08.2022. Betænkning 30.08.2022).</Char></Linea></Exitus></PunktTekst><PunktTekst><Exitus><Linea><Char formaChar="Bold">3) 2. behandling af lovforslag nr. L 206:</Char></Linea></Exitus><Exitus><Linea><Char>Forslag til lov om en ekstra økonomisk støtte til modtagere af ældrechecken, engangsbeløb til overførselsmodtagere, der har trukket sig tilbage fra arbejdsmarkedet, og engangsbeløb til uddannelsessøgende, der modtager stipendium som tillæg på grund af en funktionsnedsættelse eller som enlige forsørgere.

</Char></Linea></Exitus><Exitus><Linea><Char>Af beskæftigelsesministeren (Peter Hummelgaard).</Char></Linea></Exitus><Exitus><Linea><Char>(Fremsættelse 23.08.2022. 1. behandling 25.08.2022. Betænkning 01.09.2022).</Char></Linea></Exitus></PunktTekst></DagsordenPlan><DagsordenPunkt><MetaFTAgendaItem><ItemNo>0</ItemNo><FTCase /><FTCaseNumber /><FTCaseType>FM</FTCaseType><FTCaseStage /><ShortTitle>Punkt 0</ShortTitle></MetaFTAgendaItem><PunktTekst><Exitus><Linea><Char /></Linea></Exitus></PunktTekst><Aktivitet><Rubrica><Linea><Char>Meddelelser fra formanden</Char></Linea></Rubrica><Tale><Taler><MetaSpeakerMP tingdokID="102178"><OratorFirstName>Henrik Dam</OratorFirstName><OratorLastName>Kristensen</OratorLastName><GroupNameShort>S</GroupNameShort><OratorRole>formand</OratorRole></MetaSpeakerMP><TalerTitel><Linea><Char formaChar="Bold">Formanden</Char><Char /></Linea></TalerTitel></Taler><TaleSegment><MetaSpeechSegment><LastModified>2023-08-29T16:00:05</LastModified><EdixiStatus>Typeset</EdixiStatus><StartDateTime>2022-09-08T09:00:14</StartDateTime><EndDateTime>2022-09-08T09:01:04</EndDateTime></MetaSpeechSegment><TekstGruppe><Exitus><Linea><Char>Mødet er åbnet.</Char></Linea></Exitus></TekstGruppe><TekstGruppe><Exitus formaForma="NormalLuft"><Linea><Char>Fra Statsministeriet har jeg modtaget brev om, at det efter statsministerens indstilling ved kongelig resolution af 25.</Char></Linea><Linea><Char>august 2022 blev bestemt, at opgaver om basal it-drift og kontrakter og leverandørstyringsopgaver vedrørende outsourcet it-drift, der vedrører Udenrigsministeriet, overføres fra udenrigsministeren til finansministeren.</Char></Linea></Exitus><Exitus formaForma="NormalInd"><Linea><Char>Meddelelsen vil fremgå af www.folketingstidende.dk (jf.</Char></Linea><Linea><Char>nedenfor).</Char></Linea></Exitus></TekstGruppe><TekstGruppe><Exitus formaForma="NormalLuft"><Linea><Char>[»Folketingets formand</Char></Linea></Exitus></TekstGruppe><TekstGruppe><Exitus formaForma="NormalLuft"><Linea><Char>Efter min indstilling er det ved kongelig resolution af 25.</Char></Linea><Linea><Char>august 2022 bestemt,</Char></Linea></Exitus></TekstGruppe><TekstGruppe><Exitus formaForma="NormalLuft"><Linea><Char>at ressortansvaret for alle opgaver, kontrakter og serviceaftaler vedrørende basal it-drift af interne datacentre, netværk, servere og storage, drift af operativsystemer, standard it-arbejdsplads, servicedesk og brugeradministration, informationssikkerhedsopgaver vedrørende foranstående samt kontrakter og leverandørstyringsopgaver vedrørende outsourcet it-drift, der vedrører Udenrigsministeriet, i henhold til nærmere aftale mellem udenrigsministeren og finansministeren overføres fra udenrigsministeren til finansministeren pr.</Char></Linea><Linea><Char>1.</Char></Linea><Linea><Char>september 2022.</Char></Linea></Exitus></TekstGruppe><TekstGruppe><Exitus formaForma="NormalLuft"><Linea><Char>Jeg beder formanden underrette Folketinget herom.</Char></Linea></Exitus></TekstGruppe><TekstGruppe><Exitus formaForma="NormalLuft"><Linea><Char>Sign.</Char></Linea><Linea><Char>Mette Frederiksen</Char></Linea></Exitus><Exitus formaForma="NormalVenstre"><Linea><Char>/Carsten Madsen«].</Char></Linea></Exitus></TekstGruppe><TekstGruppe><Exitus formaForma="NormalLuft"><Linea><Char>Socialistisk Folkepartis folketingsgruppe har meddelt mig, at den til den kommende funktionsperiode, der begynder den 1.</Char></Linea><Linea><Char>oktober 2022, har udpeget Serdal Benli som statsrevisor i stedet for Holger K.</Char></Linea><Linea><Char>Nielsen.</Char></Linea></Exitus></TekstGruppe><TekstGruppe><Exitus formaForma="NormalLuft"><Linea><Char>Den pågældende er herefter valgt.</Char></Linea></Exitus></TekstGruppe></TaleSegment></Tale></Aktivitet></DagsordenPunkt><DagsordenPunkt><MetaFTAgendaItem><ItemNo>1</ItemNo><FTCase tingdokID="579605" /><FTCaseNumber>204</FTCaseNumber><FTCaseType>L</FTCaseType><FTCaseStage>BEH2</FTCaseStage><ShortTitle>2. behandling af L 204: Om nedsættelse af den almindelige elafgift i fjerde kvartal 2022 og i 2023 og forhøjelse af det maksimal</ShortTitle></MetaFTAgendaItem><PunktTekst><PreTekst><Exitus><Linea><Char>Det første punkt på dagsordenen er:</Char></Linea></Exitus></PreTekst><Exitus><Linea><Char formaChar="Bold">1) 2. behandling af lovforslag nr. L 204:</Char></Linea></Exitus><Exitus><Linea><Char formaChar="Bold">Forslag til lov om ændring af lov om afgift af elektricitet og ligningsloven. (Nedsættelse af den almindelige elafgift i fjerde kvartal 2022 og i 2023 og forhøjelse af det maksimale beskæftigelsesfradrag for indkomstårene 2022 og 2023).</Char></Linea></Exitus><Exitus><Linea><Char>Af skatteministeren (Jeppe Bruus).</Char></Linea></Exitus><Exitus><Linea><Char>(Fremsættelse 23.08.2022. 1. behandling 25.08.2022. Betænkning 01.09.2022).</Char></Linea></Exitus></PunktTekst><Aktivitet><Rubrica><Linea><Char>Forhandling</Char></Linea></Rubrica><Tale><Taler><MetaSpeakerMP tingdokID="102178"><OratorFirstName>Henrik Dam</OratorFirstName><OratorLastName>Kristensen</OratorLastName><GroupNameShort>S</GroupNameShort><OratorRole>formand</OratorRole></MetaSpeakerMP><TalerTitel><Linea><Char formaChar="Bold">Formanden</Char><Char /></Linea></TalerTitel></Taler><TaleSegment><MetaSpeechSegment><LastModified>2023-08-29T16:00:05</LastModified><EdixiStatus>Typeset</EdixiStatus><StartDateTime>2022-09-08T09:01:04</StartDateTime><EndDateTime>2022-09-08T09:01:18</EndDateTime></MetaSpeechSegment><TekstGruppe><Exitus><Linea><Char>Der er ikke stillet ændringsforslag.</Char></Linea></Exitus><Exitus formaForma="NormalInd"><Linea><Char>Er der nogen, der ønsker at udtale sig?</Char></Linea><Linea><Char>Det gør hr.</Char></Linea><Linea><Char>Søren Egge Rasmussen, Enhedslisten.</Char></Linea></Exitus></TekstGruppe></TaleSegment></Tale><Tale><Taler><MetaSpeakerMP tingdokID="103836"><OratorFirstName>Søren Egge</OratorFirstName><OratorLastName>Rasmussen</OratorLastName><GroupNameShort>EL</GroupNameShort><OratorRole>medlem</OratorRole></MetaSpeakerMP><TalerTitel><Linea><Char formaChar="Bold">Søren Egge Rasmussen</Char><Char> (EL)</Char></Linea></TalerTitel></Taler><TaleType><Linea><Char>Ordfører</Char></Linea></TaleType><TaleSegment><MetaSpeechSegment><LastModified>2023-08-29T16:00:05</LastModified><EdixiStatus>Typeset</EdixiStatus><StartDateTime>2022-09-08T09:01:18</StartDateTime><EndDateTime>2022-09-08T09:02:49</EndDateTime></MetaSpeechSegment><TekstGruppe><Exitus><Linea><Char>Det er jo korrekt, at der ikke er ændringsforslag til det her forslag om at sænke elafgiften med 4 øre.</Char></Linea><Linea><Char>Det er sådan noget, som kan hjælpe nogle danskere med et lavt forbrug.</Char></Linea><Linea><Char>Hvis man har et lavt forbrug på 2.000 kWh, er det 80 kr.</Char></Linea><Linea><Char>om året.</Char></Linea><Linea><Char>Og så kan jeg notere mig, at der er nogle partier i den offentlige debat, der gerne vil sænke afgiften fuldstændig ned til det minimale, så man sænker den med 68 øre yderligere.</Char></Linea><Linea><Char>Det er der så ikke ændringsforslag om i dag.</Char></Linea><Linea><Char>Der er så nogle partier, f.eks.</Char></Linea><Linea><Char>Venstre, der har været ude at sige, at det måske koster 3 mia.</Char></Linea><Linea><Char>kr.</Char></Linea><Linea><Char>Det er jo vigtigt, at der er korrekte tal op til et valg og også generelt.</Char></Linea><Linea><Char>Der ligger nu et svar, som siger, at det, hvis man sænker det til 0,8 øre, vil koste staten 6,8 mia.</Char></Linea><Linea><Char>kr.</Char></Linea><Linea><Char>på årsbasis i 2023, hvis det er det, man vil.</Char></Linea><Linea><Char>Det er jo et større beløb, når man ser et finanslovsforslag, hvor der er sat en pulje på 2 mia.</Char></Linea><Linea><Char>kr.</Char></Linea><Linea><Char>af til at hjælpe danskerne i en særlig situation, hvor det er prisen på både varme, el og fødevarer, der stiger.</Char></Linea></Exitus><Exitus formaForma="NormalInd"><Linea><Char>Altså, i Enhedslisten har vi den holdning, at vi som udgangspunkt ikke går ind for at sænke elafgiften; vi vil sådan set hellere øge den grønne check og målrettet hjælpe nogle lavindkomstgrupper og hjælpe nogle grupper på overførselsindkomster.</Char></Linea><Linea><Char>Men jeg synes faktisk, at det er rigtigt, at vi bruger korrekte tal, og der er så kommet et tal nu, som siger, at efter tilbageløb er det 6,8 mia.</Char></Linea><Linea><Char>kr., hvis man vil sænke elafgiften til 0,8 øre i 2023.</Char></Linea></Exitus></TekstGruppe></TaleSegment></Tale><Tale><Taler><MetaSpeakerMP tingdokID="102178"><OratorFirstName>Henrik Dam</OratorFirstName><OratorLastName>Kristensen</OratorLastName><GroupNameShort>S</GroupNameShort><OratorRole>formand</OratorRole></MetaSpeakerMP><TalerTitel><Linea><Char formaChar="Bold">Formanden</Char><Char /></Linea></TalerTitel></Taler><TaleSegment><MetaSpeechSegment><LastModified>2023-08-29T16:00:05</LastModified><EdixiStatus>Typeset</EdixiStatus><StartDateTime>2022-09-08T09:02:49</StartDateTime><EndDateTime>2022-09-08T09:02:54</EndDateTime></MetaSpeechSegment><TekstGruppe><Exitus><Linea><Char>Det gav anledning til korte bemærkninger.</Char></Linea><Linea><Char>Først er det fru Louise Schack Elholm.</Char></Linea></Exitus></TekstGruppe></TaleSegment></Tale><Tale><Taler><MetaSpeakerMP tingdokID="106936"><OratorFirstName>Louise Schack</OratorFirstName><OratorLastName>Elholm</OratorLastName><GroupNameShort>V</GroupNameShort><OratorRole>medlem</OratorRole></MetaSpeakerMP><TalerTitel><Linea><Char formaChar="Bold">Louise Schack Elholm</Char><Char> (V)</Char></Linea></TalerTitel></Taler><TaleSegment><MetaSpeechSegment><LastModified>2023-08-29T16:00:05</LastModified><EdixiStatus>Typeset</EdixiStatus><StartDateTime>2022-09-08T09:02:54</StartDateTime><EndDateTime>2022-09-08T09:03:17</EndDateTime></MetaSpeechSegment><TekstGruppe><Exitus><Linea><Char>Tak for det.</Char></Linea><Linea><Char>Det er jo rigtig fint, at hr.</Char></Linea><Linea><Char>Søren Egge Rasmussen har spurgt til, hvor meget det koster at sænke elafgiften i et helt år.</Char></Linea><Linea><Char>Nu foreslår Venstre jo, at det skal være fra den 1.</Char></Linea><Linea><Char>oktober til den 1.</Char></Linea><Linea><Char>marts.</Char></Linea><Linea><Char>Inden ordføreren går op og giver os skylden i forhold til at skulle finansiere noget, der skal vare et helt år, når vi ikke foreslår det for et helt år, så vil jeg bare høre, om ordføreren normalt synes, at det er god kutyme, at man rent faktisk læser de forslag, man angriber, før man angriber dem.</Char></Linea></Exitus></TekstGruppe></TaleSegment></Tale><Tale><Taler><MetaSpeakerMP tingdokID="102178"><OratorFirstName>Henrik Dam</OratorFirstName><OratorLastName>Kristensen</OratorLastName><GroupNameShort>S</GroupNameShort><OratorRole>formand</OratorRole></MetaSpeakerMP><TalerTitel><Linea><Char formaChar="Bold">Formanden</Char><Char /></Linea></TalerTitel></Taler><TaleSegment><MetaSpeechSegment><LastModified>2023-08-29T16:00:05</LastModified><EdixiStatus>Typeset</EdixiStatus><StartDateTime>2022-09-08T09:03:17</StartDateTime><EndDateTime>2022-09-08T09:03:21</EndDateTime></MetaSpeechSegment><TekstGruppe><Exitus><Linea><Char>Ordføreren.</Char></Linea></Exitus></TekstGruppe></TaleSegment></Tale><Tale><Taler><MetaSpeakerMP tingdokID="103836"><OratorFirstName>Søren Egge</OratorFirstName><OratorLastName>Rasmussen</OratorLastName><GroupNameShort>EL</GroupNameShort><OratorRole>medlem</OratorRole></MetaSpeakerMP><TalerTitel><Linea><Char formaChar="Bold">Søren Egge Rasmussen</Char><Char> (EL)</Char></Linea></TalerTitel></Taler><TaleSegment><MetaSpeechSegment><LastModified>2023-08-29T16:00:05</LastModified><EdixiStatus>Typeset</EdixiStatus><StartDateTime>2022-09-08T09:03:21</StartDateTime><EndDateTime>2022-09-08T09:03:31</EndDateTime></MetaSpeechSegment><TekstGruppe><Exitus><Linea><Char>Jeg synes altid, det er godt at oplyse på et oplyst grundlag.</Char></Linea><Linea><Char>Så det er fint at blive korrekset om, at Venstres politik er så kortsigtet, at den kun gælder for et halvt år.</Char></Linea></Exitus></TekstGruppe></TaleSegment></Tale><Tale><Taler><MetaSpeakerMP tingdokID="102178"><OratorFirstName>Henrik Dam</OratorFirstName><OratorLastName>Kristensen</OratorLastName><GroupNameShort>S</GroupNameShort><OratorRole>formand</OratorRole></MetaSpeakerMP><TalerTitel><Linea><Char formaChar="Bold">Formanden</Char><Char /></Linea></TalerTitel></Taler><TaleSegment><MetaSpeechSegment><LastModified>2023-08-29T16:00:05</LastModified><EdixiStatus>Typeset</EdixiStatus><StartDateTime>2022-09-08T09:03:31</StartDateTime><EndDateTime>2022-09-08T09:03:34</EndDateTime></MetaSpeechSegment><TekstGruppe><Exitus><Linea><Char>Fru Louise Schack Elholm.</Char></Linea></Exitus></TekstGruppe></TaleSegment></Tale><Tale><Taler><MetaSpeakerMP tingdokID="106936"><OratorFirstName>Louise Schack</OratorFirstName><OratorLastName>Elholm</OratorLastName><GroupNameShort>V</GroupNameShort><OratorRole>medlem</OratorRole></MetaSpeakerMP><TalerTitel><Linea><Char formaChar="Bold">Louise Schack Elholm</Char><Char> (V)</Char></Linea></TalerTitel></Taler><TaleSegment><MetaSpeechSegment><LastModified>2023-08-29T16:00:05</LastModified><EdixiStatus>Typeset</EdixiStatus><StartDateTime>2022-09-08T09:03:34</StartDateTime><EndDateTime>2022-09-08T09:03:49</EndDateTime></MetaSpeechSegment><TekstGruppe><Exitus><Linea><Char>Jeg vil bare høre, om det er normalt, at man angriber uden at have læst forslaget først.</Char></Linea><Linea><Char>Det synes jeg jo egentlig er dårlig stil.</Char></Linea><Linea><Char>Altså, grundlæggende foreslår vi ting, og så forventer vi, at hvis vi bliver angrebet for det, bliver det på det faktuelle grundlag og ikke på et eller andet, man har opsat.</Char></Linea></Exitus></TekstGruppe></TaleSegment></Tale><Tale><Taler><MetaSpeakerMP tingdokID="102178"><OratorFirstName>Henrik Dam</OratorFirstName><OratorLastName>Kristensen</OratorLastName><GroupNameShort>S</GroupNameShort><OratorRole>formand</OratorRole></MetaSpeakerMP><TalerTitel><Linea><Char formaChar="Bold">Formanden</Char><Char /></Linea></TalerTitel></Taler><TaleSegment><MetaSpeechSegment><LastModified>2023-08-29T16:00:05</LastModified><EdixiStatus>Typeset</EdixiStatus><StartDateTime>2022-09-08T09:03:49</StartDateTime><EndDateTime>2022-09-08T09:03:52</EndDateTime></MetaSpeechSegment><TekstGruppe><Exitus><Linea><Char>Ordføreren.</Char></Linea></Exitus></TekstGruppe></TaleSegment></Tale><Tale><Taler><MetaSpeakerMP tingdokID="103836"><OratorFirstName>Søren Egge</OratorFirstName><OratorLastName>Rasmussen</OratorLastName><GroupNameShort>EL</GroupNameShort><OratorRole>medlem</OratorRole></MetaSpeakerMP><TalerTitel><Linea><Char formaChar="Bold">Søren Egge Rasmussen</Char><Char> (EL)</Char></Linea></TalerTitel></Taler><TaleSegment><MetaSpeechSegment><LastModified>2023-08-29T16:00:05</LastModified><EdixiStatus>Typeset</EdixiStatus><StartDateTime>2022-09-08T09:03:52</StartDateTime><EndDateTime>2022-09-08T09:04:04</EndDateTime></MetaSpeechSegment><TekstGruppe><Exitus><Linea><Char>Det er da rigtig dejligt at blive korrekset i salen.</Char></Linea><Linea><Char>Og så må jeg stadig væk konstatere, at Venstre har en politik, der kun rækker et halvt år frem.</Char></Linea><Linea><Char>I Enhedslisten har vi en langsigtet politik, og det er jo derfor, vi gerne vil ind og justere på den grønne check.</Char></Linea></Exitus></TekstGruppe></TaleSegment></Tale><Tale><Taler><MetaSpeakerMP tingdokID="102178"><OratorFirstName>Henrik Dam</OratorFirstName><OratorLastName>Kristensen</OratorLastName><GroupNameShort>S</GroupNameShort><OratorRole>formand</OratorRole></MetaSpeakerMP><TalerTitel><Linea><Char formaChar="Bold">Formanden</Char><Char /></Linea></TalerTitel></Taler><TaleSegment><MetaSpeechSegment><LastModified>2023-08-29T16:00:05</LastModified><EdixiStatus>Typeset</EdixiStatus><StartDateTime>2022-09-08T09:04:04</StartDateTime><EndDateTime>2022-09-08T09:04:06</EndDateTime></MetaSpeechSegment><TekstGruppe><Exitus><Linea><Char>Så er det hr.</Char></Linea><Linea><Char>Troels Lund Poulsen.</Char></Linea></Exitus></TekstGruppe></TaleSegment></Tale><Tale><Taler><MetaSpeakerMP tingdokID="100513"><OratorFirstName>Troels Lund</OratorFirstName><OratorLastName>Poulsen</OratorLastName><GroupNameShort>V</GroupNameShort><OratorRole>medlem</OratorRole></MetaSpeakerMP><TalerTitel><Linea><Char formaChar="Bold">Troels Lund Poulsen</Char><Char> (V)</Char></Linea></TalerTitel></Taler><TaleSegment><MetaSpeechSegment><LastModified>2023-08-29T16:00:05</LastModified><EdixiStatus>Typeset</EdixiStatus><StartDateTime>2022-09-08T09:04:06</StartDateTime><EndDateTime>2022-09-08T09:04:21</EndDateTime></MetaSpeechSegment><TekstGruppe><Exitus><Linea><Char>Tak for, at Enhedslisten har en langsigtet politik.</Char></Linea><Linea><Char>Det er meget betryggende, og det er nok også meget dyrt.</Char></Linea><Linea><Char>Men er hr.</Char></Linea><Linea><Char>Søren Egge Rasmussen fra Enhedslisten enig i, at det er en god idé at sænke elafgiften, sådan som Venstre har foreslået?</Char></Linea></Exitus></TekstGruppe></TaleSegment></Tale><Tale><Taler><MetaSpeakerMP tingdokID="102178"><OratorFirstName>Henrik Dam</OratorFirstName><OratorLastName>Kristensen</OratorLastName><GroupNameShort>S</GroupNameShort><OratorRole>formand</OratorRole></MetaSpeakerMP><TalerTitel><Linea><Char formaChar="Bold">Formanden</Char><Char /></Linea></TalerTitel></Taler><TaleSegment><MetaSpeechSegment><LastModified>2023-08-29T16:00:05</LastModified><EdixiStatus>Typeset</EdixiStatus><StartDateTime>2022-09-08T09:04:21</StartDateTime><EndDateTime>2022-09-08T09:04:23</EndDateTime></MetaSpeechSegment><TekstGruppe><Exitus><Linea><Char>Ordføreren.</Char></Linea></Exitus></TekstGruppe></TaleSegment></Tale><Tale><Taler><MetaSpeakerMP tingdokID="103836"><OratorFirstName>Søren Egge</OratorFirstName><OratorLastName>Rasmussen</OratorLastName><GroupNameShort>EL</GroupNameShort><OratorRole>medlem</OratorRole></MetaSpeakerMP><TalerTitel><Linea><Char formaChar="Bold">Søren Egge Rasmussen</Char><Char> (EL)</Char></Linea></TalerTitel></Taler><TaleSegment><MetaSpeechSegment><LastModified>2023-08-29T16:00:05</LastModified><EdixiStatus>Typeset</EdixiStatus><StartDateTime>2022-09-08T09:04:23</StartDateTime><EndDateTime>2022-09-08T09:05:22</EndDateTime></MetaSpeechSegment><TekstGruppe><Exitus><Linea><Char>Vi vil hellere gøre det langt mere målrettet, når vi har begrænsede ressourcer til at hjælpe danskerne.</Char></Linea><Linea><Char>Det er derfor, at vi er kommet frem til den konklusion, at det er bedre at hæve den grønne check, så vi går ind og giver et skattemæssigt fradrag til de pensionister, som har mindst – ikke til samtlige pensionister – til førtidspensionister, kontanthjælpsmodtagere, til vores studerende på su og til lavtlønnede.</Char></Linea><Linea><Char>Der er mange mennesker, der ikke har et fuldtidsarbejde, men har et deltidsarbejde med en relativt lav løn, og de bør sådan set også have et højere skattemæssigt fradrag via den grønne check.</Char></Linea><Linea><Char>Det synes vi er det bedste greb, når vi ikke har ubegrænsede midler.</Char></Linea></Exitus><Exitus formaForma="NormalInd"><Linea><Char>Men vi er også helt opmærksomme på, at vi er i en særlig situation, hvor rigtig mange danskere er pressede på deres økonomi – en økonomi, som de normalt har overskud til at have indsigt i – for der er så mange ting, der er steget.</Char></Linea><Linea><Char>Vi er sådan set meget fokuserede på at lave en god finanslov sammen med regeringen, som løser mange af problemerne.</Char></Linea></Exitus></TekstGruppe></TaleSegment></Tale><Tale><Taler><MetaSpeakerMP tingdokID="102178"><OratorFirstName>Henrik Dam</OratorFirstName><OratorLastName>Kristensen</OratorLastName><GroupNameShort>S</GroupNameShort><OratorRole>formand</OratorRole></MetaSpeakerMP><TalerTitel><Linea><Char formaChar="Bold">Formanden</Char><Char /></Linea></TalerTitel></Taler><TaleSegment><MetaSpeechSegment><LastModified>2023-08-29T16:00:05</LastModified><EdixiStatus>Typeset</EdixiStatus><StartDateTime>2022-09-08T09:05:22</StartDateTime><EndDateTime>2022-09-08T09:05:23</EndDateTime></MetaSpeechSegment><TekstGruppe><Exitus><Linea><Char>Hr.</Char></Linea><Linea><Char>Troels Lund Poulsen.</Char></Linea></Exitus></TekstGruppe></TaleSegment></Tale><Tale><Taler><MetaSpeakerMP tingdokID="100513"><OratorFirstName>Troels Lund</OratorFirstName><OratorLastName>Poulsen</OratorLastName><GroupNameShort>V</GroupNameShort><OratorRole>medlem</OratorRole></MetaSpeakerMP><TalerTitel><Linea><Char formaChar="Bold">Troels Lund Poulsen</Char><Char> (V)</Char></Linea></TalerTitel></Taler><TaleSegment><MetaSpeechSegment><LastModified>2023-08-29T16:00:05</LastModified><EdixiStatus>Typeset</EdixiStatus><StartDateTime>2022-09-08T09:05:23</StartDateTime><EndDateTime>2022-09-08T09:05:31</EndDateTime></MetaSpeechSegment><TekstGruppe><Exitus><Linea><Char>Jeg blev lidt forvirret og forstod aldrig helt svaret.</Char></Linea><Linea><Char>Var svaret, at man kan støtte Venstres forslag – ja eller nej?</Char></Linea></Exitus></TekstGruppe></TaleSegment></Tale><Tale><Taler><MetaSpeakerMP tingdokID="102178"><OratorFirstName>Henrik Dam</OratorFirstName><OratorLastName>Kristensen</OratorLastName><GroupNameShort>S</GroupNameShort><OratorRole>formand</OratorRole></MetaSpeakerMP><TalerTitel><Linea><Char formaChar="Bold">Formanden</Char><Char /></Linea></TalerTitel></Taler><TaleSegment><MetaSpeechSegment><LastModified>2023-08-29T16:00:05</LastModified><EdixiStatus>Typeset</EdixiStatus><StartDateTime>2022-09-08T09:05:31</StartDateTime><EndDateTime>2022-09-08T09:05:34</EndDateTime></MetaSpeechSegment><TekstGruppe><Exitus><Linea><Char>Ordføreren.</Char></Linea></Exitus></TekstGruppe></TaleSegment></Tale><Tale><Taler><MetaSpeakerMP tingdokID="103836"><OratorFirstName>Søren Egge</OratorFirstName><OratorLastName>Rasmussen</OratorLastName><GroupNameShort>EL</GroupNameShort><OratorRole>medlem</OratorRole></MetaSpeakerMP><TalerTitel><Linea><Char formaChar="Bold">Søren Egge Rasmussen</Char><Char> (EL)</Char></Linea></TalerTitel></Taler><TaleSegment><MetaSpeechSegment><LastModified>2023-08-29T16:00:05</LastModified><EdixiStatus>Typeset</EdixiStatus><StartDateTime>2022-09-08T09:05:34</StartDateTime><EndDateTime>2022-09-08T09:06:04</EndDateTime></MetaSpeechSegment><TekstGruppe><Exitus><Linea><Char>Det kan vi ikke støtte, for vi synes, det er meget bedre at hæve den grønne check målrettet nogle af de grupper i samfundet, der har allermindst.</Char></Linea><Linea><Char>Så vi siger som udgangspunkt klart nej, men vi er også der, hvor vi meget gerne vil gennemføre en finanslovsforhandling.</Char></Linea><Linea><Char>Det kan vi så blive forstyrret i, fordi der er et enkelt parti, som har holdt sommerferie, og som ikke længere har helt tillid til regeringen.</Char></Linea><Linea><Char>Det er så det, vi får afklaret i løbet af relativt kort tid, altså om det ender der.</Char></Linea><Linea><Char>Men vores ønske er at lave en god finanslov, hvor vi tager hånd om de økonomiske problemer.</Char></Linea></Exitus></TekstGruppe></TaleSegment></Tale><Tale><Taler><MetaSpeakerMP tingdokID="102178"><OratorFirstName>Henrik Dam</OratorFirstName><OratorLastName>Kristensen</OratorLastName><GroupNameShort>S</GroupNameShort><OratorRole>formand</OratorRole></MetaSpeakerMP><TalerTitel><Linea><Char formaChar="Bold">Formanden</Char><Char /></Linea></TalerTitel></Taler><TaleSegment><MetaSpeechSegment><LastModified>2023-08-29T16:00:05</LastModified><EdixiStatus>Typeset</EdixiStatus><StartDateTime>2022-09-08T09:06:04</StartDateTime><EndDateTime>2022-09-08T09:06:06</EndDateTime></MetaSpeechSegment><TekstGruppe><Exitus><Linea><Char>Så er det hr.</Char></Linea><Linea><Char>René Christensen, Dansk Folkeparti.</Char></Linea></Exitus></TekstGruppe></TaleSegment></Tale><Tale><Taler><MetaSpeakerMP tingdokID="106955"><OratorFirstName>René</OratorFirstName><OratorLastName>Christensen</OratorLastName><GroupNameShort>DF</GroupNameShort><OratorRole>medlem</OratorRole></MetaSpeakerMP><TalerTitel><Linea><Char formaChar="Bold">René Christensen</Char><Char> (DF)</Char></Linea></TalerTitel></Taler><TaleSegment><MetaSpeechSegment><LastModified>2023-08-29T16:00:05</LastModified><EdixiStatus>Typeset</EdixiStatus><StartDateTime>2022-09-08T09:06:06</StartDateTime><EndDateTime>2022-09-08T09:06:18</EndDateTime></MetaSpeechSegment><TekstGruppe><Exitus><Linea><Char>Tak for det.</Char></Linea><Linea><Char>Den grønne check er jo for pensionister på 875 kr.</Char></Linea><Linea><Char>Hvad er det, den grønne check så skal hæves til, og hvad koster det forslag, Enhedslisten har?</Char></Linea></Exitus></TekstGruppe></TaleSegment></Tale><Tale><Taler><MetaSpeakerMP tingdokID="102178"><OratorFirstName>Henrik Dam</OratorFirstName><OratorLastName>Kristensen</OratorLastName><GroupNameShort>S</GroupNameShort><OratorRole>formand</OratorRole></MetaSpeakerMP><TalerTitel><Linea><Char formaChar="Bold">Formanden</Char><Char /></Linea></TalerTitel></Taler><TaleSegment><MetaSpeechSegment><LastModified>2023-08-29T16:00:05</LastModified><EdixiStatus>Typeset</EdixiStatus><StartDateTime>2022-09-08T09:06:18</StartDateTime><EndDateTime>2022-09-08T09:06:20</EndDateTime></MetaSpeechSegment><TekstGruppe><Exitus><Linea><Char>Ordføreren.</Char></Linea></Exitus></TekstGruppe></TaleSegment></Tale><Tale><Taler><MetaSpeakerMP tingdokID="103836"><OratorFirstName>Søren Egge</OratorFirstName><OratorLastName>Rasmussen</OratorLastName><GroupNameShort>EL</GroupNameShort><OratorRole>medlem</OratorRole></MetaSpeakerMP><TalerTitel><Linea><Char formaChar="Bold">Søren Egge Rasmussen</Char><Char> (EL)</Char></Linea></TalerTitel></Taler><TaleSegment><MetaSpeechSegment><LastModified>2023-08-29T16:00:05</LastModified><EdixiStatus>Typeset</EdixiStatus><StartDateTime>2022-09-08T09:06:20</StartDateTime><EndDateTime>2022-09-08T09:07:00</EndDateTime></MetaSpeechSegment><TekstGruppe><Exitus><Linea><Char>Jamen det er vi sådan set i proces med at komme med et udspil på.</Char></Linea><Linea><Char>Det er faktisk et rigtig godt spørgsmål, for vi kommer fra Enhedslistens side altid med fuldt finansierede forslag.</Char></Linea><Linea><Char>Så vi kan ikke sætte det præcise milliardbeløb på, men når det kommer, vil det være fuldt finansieret, ligesom det plejer at være.</Char></Linea><Linea><Char>Vi har jo lavet nogle aftaler sammen med regeringen og Dansk Folkeparti, og det kan da være, det er en aftale, vi skal lave sammen med René Christensen.</Char></Linea><Linea><Char>Det er jo svært nu om dage at tælle mandater hver eneste dag, altså hvordan fordelingen lige er, men vi ser ikke noget problem i at lave aftaler med DF, som tager hånd om de mennesker med de laveste indtægter.</Char></Linea></Exitus></TekstGruppe></TaleSegment></Tale><Tale><Taler><MetaSpeakerMP tingdokID="102178"><OratorFirstName>Henrik Dam</OratorFirstName><OratorLastName>Kristensen</OratorLastName><GroupNameShort>S</GroupNameShort><OratorRole>formand</OratorRole></MetaSpeakerMP><TalerTitel><Linea><Char formaChar="Bold">Formanden</Char><Char /></Linea></TalerTitel></Taler><TaleSegment><MetaSpeechSegment><LastModified>2023-08-29T16:00:05</LastModified><EdixiStatus>Typeset</EdixiStatus><StartDateTime>2022-09-08T09:07:00</StartDateTime><EndDateTime>2022-09-08T09:07:08</EndDateTime></MetaSpeechSegment><TekstGruppe><Exitus><Linea><Char>Jeg gør opmærksom på, at man i henhold til forretningsordenen skal være lidt tilbageholdende med ytringer i Folketingssalen.</Char></Linea></Exitus><Exitus formaForma="NormalInd"><Linea><Char>Hr.</Char></Linea><Linea><Char>René Christensen, værsgo.</Char></Linea></Exitus></TekstGruppe></TaleSegment></Tale><Tale><Taler><MetaSpeakerMP tingdokID="106955"><OratorFirstName>René</OratorFirstName><OratorLastName>Christensen</OratorLastName><GroupNameShort>DF</GroupNameShort><OratorRole>medlem</OratorRole></MetaSpeakerMP><TalerTitel><Linea><Char formaChar="Bold">René Christensen</Char><Char> (DF)</Char></Linea></TalerTitel></Taler><TaleSegment><MetaSpeechSegment><LastModified>2023-08-29T16:00:05</LastModified><EdixiStatus>Typeset</EdixiStatus><StartDateTime>2022-09-08T09:07:08</StartDateTime><EndDateTime>2022-09-08T09:07:45</EndDateTime></MetaSpeechSegment><TekstGruppe><Exitus><Linea><Char>Det skal man være, men nogle gange er det jo svært at holde det tilbage.</Char></Linea><Linea><Char>Nu er der et forslag fra Venstre, som vi i Dansk Folkeparti faktisk synes er ret positivt.</Char></Linea><Linea><Char>Det er ikke kun folk på overførselsindkomster, der er presset af de energipriser, vi ser nu, det er der rigtig mange danskere der er, og det gælder også de husstande, hvor der er to voksne, der går på arbejde.</Char></Linea><Linea><Char>Når Enhedslisten så går op og taler om den grønne check, er det interessant, men det er jo interessant, om det er 200 kr.</Char></Linea><Linea><Char>mere om året, man får, eller om det er 500 kr.</Char></Linea><Linea><Char>mere om måneden, man får, og når Enhedslisten nu tager ordet til sådan en debat her, bliver de da nødt til også at sige, hvad det er, de vil i stedet for.</Char></Linea></Exitus></TekstGruppe></TaleSegment></Tale><Tale><Taler><MetaSpeakerMP tingdokID="102178"><OratorFirstName>Henrik Dam</OratorFirstName><OratorLastName>Kristensen</OratorLastName><GroupNameShort>S</GroupNameShort><OratorRole>formand</OratorRole></MetaSpeakerMP><TalerTitel><Linea><Char formaChar="Bold">Formanden</Char><Char /></Linea></TalerTitel></Taler><TaleSegment><MetaSpeechSegment><LastModified>2023-08-29T16:00:05</LastModified><EdixiStatus>Typeset</EdixiStatus><StartDateTime>2022-09-08T09:07:45</StartDateTime><EndDateTime>2022-09-08T09:07:48</EndDateTime></MetaSpeechSegment><TekstGruppe><Exitus><Linea><Char>Tak.</Char></Linea><Linea><Char>Ordføreren, værsgo.</Char></Linea></Exitus></TekstGruppe></TaleSegment></Tale><Tale><Taler><MetaSpeakerMP tingdokID="103836"><OratorFirstName>Søren Egge</OratorFirstName><OratorLastName>Rasmussen</OratorLastName><GroupNameShort>EL</GroupNameShort><OratorRole>medlem</OratorRole></MetaSpeakerMP><TalerTitel><Linea><Char formaChar="Bold">Søren Egge Rasmussen</Char><Char> (EL)</Char></Linea></TalerTitel></Taler><TaleSegment><MetaSpeechSegment><LastModified>2023-08-29T16:00:05</LastModified><EdixiStatus>Typeset</EdixiStatus><StartDateTime>2022-09-08T09:07:48</StartDateTime><EndDateTime>2022-09-08T09:08:15</EndDateTime></MetaSpeechSegment><TekstGruppe><Exitus><Linea><Char>Jamen når vi arbejder med udspil i Enhedslisten, har jeg da fuld respekt for, at der er nogle processer omkring det.</Char></Linea><Linea><Char>Jeg er rigtig glad for, at der vil være en stor interesse, når vi lancerer det inflationsudspil, som vi arbejder med.</Char></Linea><Linea><Char>Det er så ikke lige i dag, vi kommer med det udspil, for der er en finanslovsdebat, der nok tager hele fokus i dag, så vi vælger en anden dag til at lancere det.</Char></Linea><Linea><Char>Men jeg er glad for den store forhåndsinteresse, der er.</Char></Linea></Exitus></TekstGruppe></TaleSegment></Tale><Tale><Taler><MetaSpeakerMP tingdokID="102178"><OratorFirstName>Henrik Dam</OratorFirstName><OratorLastName>Kristensen</OratorLastName><GroupNameShort>S</GroupNameShort><OratorRole>formand</OratorRole></MetaSpeakerMP><TalerTitel><Linea><Char formaChar="Bold">Formanden</Char><Char /></Linea></TalerTitel></Taler><TaleSegment><MetaSpeechSegment><LastModified>2023-08-29T16:00:05</LastModified><EdixiStatus>Typeset</EdixiStatus><StartDateTime>2022-09-08T09:08:15</StartDateTime><EndDateTime>2022-09-08T09:08:21</EndDateTime></MetaSpeechSegment><TekstGruppe><Exitus><Linea><Char>Hr.</Char></Linea><Linea><Char>Jan E.</Char></Linea><Linea><Char>Jørgensen, Venstre.</Char></Linea></Exitus></TekstGruppe></TaleSegment></Tale><Tale><Taler><MetaSpeakerMP tingdokID="519121"><OratorFirstName>Jan E.</OratorFirstName><OratorLastName>Jørgensen</OratorLastName><GroupNameShort>V</GroupNameShort><OratorRole>medlem</OratorRole></MetaSpeakerMP><TalerTitel><Linea><Char formaChar="Bold">Jan E. Jørgensen</Char><Char> (V)</Char></Linea></TalerTitel></Taler><TaleSegment><MetaSpeechSegment><LastModified>2023-08-29T16:00:05</LastModified><EdixiStatus>Typeset</EdixiStatus><StartDateTime>2022-09-08T09:08:21</StartDateTime><EndDateTime>2022-09-08T09:08:42</EndDateTime></MetaSpeechSegment><TekstGruppe><Exitus><Linea><Char>Jamen altså, vi kommer jo længere og længere.</Char></Linea><Linea><Char>Enhedslisten har nu fundet ud af, at hvis man foreslår noget for mindre end et år, koster det ikke lige så meget, som når man foreslår det for et helt år.</Char></Linea><Linea><Char>Så vi er jo allerede nået langt i den nationaløkonomiske forståelse hos Enhedslisten.</Char></Linea></Exitus><Exitus formaForma="NormalInd"><Linea><Char>Men jeg kan så også forstå, at det, Enhedslisten selv foreslår, efter at man nu har skoset Venstre for, at nogle tal ikke passede, ved Enhedslisten simpelt hen slet ikke hvad koster.</Char></Linea><Linea><Char>Var det korrekt forstået?</Char></Linea></Exitus></TekstGruppe></TaleSegment></Tale><Tale><Taler><MetaSpeakerMP tingdokID="102178"><OratorFirstName>Henrik Dam</OratorFirstName><OratorLastName>Kristensen</OratorLastName><GroupNameShort>S</GroupNameShort><OratorRole>formand</OratorRole></MetaSpeakerMP><TalerTitel><Linea><Char formaChar="Bold">Formanden</Char><Char /></Linea></TalerTitel></Taler><TaleSegment><MetaSpeechSegment><LastModified>2023-08-29T16:00:05</LastModified><EdixiStatus>Typeset</EdixiStatus><StartDateTime>2022-09-08T09:08:42</StartDateTime><EndDateTime>2022-09-08T09:08:45</EndDateTime></MetaSpeechSegment><TekstGruppe><Exitus><Linea><Char>Ordføreren.</Char></Linea></Exitus></TekstGruppe></TaleSegment></Tale><Tale><Taler><MetaSpeakerMP tingdokID="103836"><OratorFirstName>Søren Egge</OratorFirstName><OratorLastName>Rasmussen</OratorLastName><GroupNameShort>EL</GroupNameShort><OratorRole>medlem</OratorRole></MetaSpeakerMP><TalerTitel><Linea><Char formaChar="Bold">Søren Egge Rasmussen</Char><Char> (EL)</Char></Linea></TalerTitel></Taler><TaleSegment><MetaSpeechSegment><LastModified>2023-08-29T16:00:05</LastModified><EdixiStatus>Typeset</EdixiStatus><StartDateTime>2022-09-08T09:08:45</StartDateTime><EndDateTime>2022-09-08T09:09:36</EndDateTime></MetaSpeechSegment><TekstGruppe><Exitus><Linea><Char>Det er helt korrekt forstået, at det, når vi kommer med udspil, så er fuldt finansieret, og det udspil kommer ikke i dag, fordi der er en finanslovsdebat.</Char></Linea></Exitus><Exitus formaForma="NormalInd"><Linea><Char>Lige nu har vi så et lille lovforslag, hvor vi sænker elafgiften med 4 øre, som Enhedslisten stemmer for, og det er ikke, fordi vi synes, det er det allervigtigste, men det kan så hjælpe nogle danskere med et lavt elforbrug med en udgift, der er 80 kr.</Char></Linea><Linea><Char>mindre.</Char></Linea><Linea><Char>Hvis man går ned ad det der spor med fuldstændig at afvikle elafgiften, er det noget, som betyder, at det, hvis man har et lille forbrug på 2.000 kW, så vil være ca.</Char></Linea><Linea><Char>1.300 kr.</Char></Linea><Linea><Char>om året, man sparer, og det er jo et væsentligt beløb.</Char></Linea></Exitus><Exitus formaForma="NormalInd"><Linea><Char>Der er det bare, vi siger, at vi, når vi skal op at bruge store beløb på at hjælpe danskerne, så hellere vil gøre det meget målrettet.</Char></Linea><Linea><Char>Og det er det, vi kan gøre med den grønne check, og vi kan gøre det på en måde, sådan at man ikke kommer ud i sager, der minder om det med varmechecken, fordi der er et system til den grønne check i vores store håndtering af den slags skattemæssige fradrag.</Char></Linea></Exitus></TekstGruppe></TaleSegment></Tale><Tale><Taler><MetaSpeakerMP tingdokID="102178"><OratorFirstName>Henrik Dam</OratorFirstName><OratorLastName>Kristensen</OratorLastName><GroupNameShort>S</GroupNameShort><OratorRole>formand</OratorRole></MetaSpeakerMP><TalerTitel><Linea><Char formaChar="Bold">Formanden</Char><Char /></Linea></TalerTitel></Taler><TaleSegment><MetaSpeechSegment><LastModified>2023-08-29T16:00:05</LastModified><EdixiStatus>Typeset</EdixiStatus><StartDateTime>2022-09-08T09:09:36</StartDateTime><EndDateTime>2022-09-08T09:09:40</EndDateTime></MetaSpeechSegment><TekstGruppe><Exitus><Linea><Char>Hr.</Char></Linea><Linea><Char>Jan E.</Char></Linea><Linea><Char>Jørgensen.</Char></Linea></Exitus></TekstGruppe></TaleSegment></Tale><Tale><Taler><MetaSpeakerMP tingdokID="519121"><OratorFirstName>Jan E.</OratorFirstName><OratorLastName>Jørgensen</OratorLastName><GroupNameShort>V</GroupNameShort><OratorRole>medlem</OratorRole></MetaSpeakerMP><TalerTitel><Linea><Char formaChar="Bold">Jan E. Jørgensen</Char><Char> (V)</Char></Linea></TalerTitel></Taler><TaleSegment><MetaSpeechSegment><LastModified>2023-08-29T16:00:05</LastModified><EdixiStatus>Typeset</EdixiStatus><StartDateTime>2022-09-08T09:09:40</StartDateTime><EndDateTime>2022-09-08T09:09:57</EndDateTime></MetaSpeechSegment><TekstGruppe><Exitus><Linea><Char>Det er bare for at forstå det helt rigtigt:</Char></Linea><Linea><Char>Enhedslisten ønsker at hjælpe folk, der døjer med at betale for deres elregning, men det er altså kun nogle folk, kun folk på overførselsindkomst osv., mens folk i lavtlønsjob og andre ønsker Enhedslisten ikke at hjælpe?</Char></Linea><Linea><Char>Er det sådan, man må forstå Enhedslistens politik?</Char></Linea></Exitus></TekstGruppe></TaleSegment></Tale><Tale><Taler><MetaSpeakerMP tingdokID="102178"><OratorFirstName>Henrik Dam</OratorFirstName><OratorLastName>Kristensen</OratorLastName><GroupNameShort>S</GroupNameShort><OratorRole>formand</OratorRole></MetaSpeakerMP><TalerTitel><Linea><Char formaChar="Bold">Formanden</Char><Char /></Linea></TalerTitel></Taler><TaleSegment><MetaSpeechSegment><LastModified>2023-08-29T16:00:05</LastModified><EdixiStatus>Typeset</EdixiStatus><StartDateTime>2022-09-08T09:09:57</StartDateTime><EndDateTime>2022-09-08T09:09:59</EndDateTime></MetaSpeechSegment><TekstGruppe><Exitus><Linea><Char>Ordføreren.</Char></Linea></Exitus></TekstGruppe></TaleSegment></Tale><Tale><Taler><MetaSpeakerMP tingdokID="103836"><OratorFirstName>Søren Egge</OratorFirstName><OratorLastName>Rasmussen</OratorLastName><GroupNameShort>EL</GroupNameShort><OratorRole>medlem</OratorRole></MetaSpeakerMP><TalerTitel><Linea><Char formaChar="Bold">Søren Egge Rasmussen</Char><Char> (EL)</Char></Linea></TalerTitel></Taler><TaleSegment><MetaSpeechSegment><LastModified>2023-08-29T16:00:05</LastModified><EdixiStatus>Typeset</EdixiStatus><StartDateTime>2022-09-08T09:09:59</StartDateTime><EndDateTime>2022-09-08T09:10:31</EndDateTime></MetaSpeechSegment><TekstGruppe><Exitus><Linea><Char>Vi er i en særlig situation, og hvor jeg rigtig gerne i en finanslovsaftale vil håndtere de udfordringer, som danskerne står over for, og som er en helt uhørt alvorlig situation, hvor prisen på både el, varme, fødevarer og diesel er steget, kan vi ikke lige håndtere det på to hurtige spørgsmål her.</Char></Linea><Linea><Char>Vores prioritet er så at hjælpe de mennesker med de laveste indtægter.</Char></Linea><Linea><Char>Vi er godt klar over, at der også er andre, som har problemer, men jeg har ikke set nogen partier komme med et samlet forslag, som løser de økonomiske problemer for samtlige danskere.</Char></Linea></Exitus></TekstGruppe></TaleSegment></Tale><Tale><Taler><MetaSpeakerMP tingdokID="102178"><OratorFirstName>Henrik Dam</OratorFirstName><OratorLastName>Kristensen</OratorLastName><GroupNameShort>S</GroupNameShort><OratorRole>formand</OratorRole></MetaSpeakerMP><TalerTitel><Linea><Char formaChar="Bold">Formanden</Char><Char /></Linea></TalerTitel></Taler><TaleSegment><MetaSpeechSegment><LastModified>2023-08-29T16:00:05</LastModified><EdixiStatus>Typeset</EdixiStatus><StartDateTime>2022-09-08T09:10:31</StartDateTime><EndDateTime>2022-09-08T09:10:38</EndDateTime></MetaSpeechSegment><TekstGruppe><Exitus><Linea><Char>Hans Kristian Skibby, Danmarksdemokraterne.</Char></Linea></Exitus></TekstGruppe></TaleSegment></Tale><Tale><Taler><MetaSpeakerMP tingdokID="102295"><OratorFirstName>Hans Kristian</OratorFirstName><OratorLastName>Skibby</OratorLastName><GroupNameShort>DD</GroupNameShort><OratorRole>medlem</OratorRole></MetaSpeakerMP><TalerTitel><Linea><Char formaChar="Bold">Hans Kristian Skibby</Char><Char> (DD)</Char></Linea></TalerTitel></Taler><TaleSegment><MetaSpeechSegment><LastModified>2023-08-29T16:00:05</LastModified><EdixiStatus>Typeset</EdixiStatus><StartDateTime>2022-09-08T09:10:38</StartDateTime><EndDateTime>2022-09-08T09:11:21</EndDateTime></MetaSpeechSegment><TekstGruppe><Exitus><Linea><Char>Tak, hr.</Char></Linea><Linea><Char>formand.</Char></Linea><Linea><Char>Jeg tænker lidt på den situation, vi har med elafregningen i Danmark i dag.</Char></Linea><Linea><Char>For det var jo sådan, at man indgik en aftale omkring produktionen i den danske Nordsø for ikke så forfærdelig længe siden vedrørende en hurtigere udfasning af dansk gasproduktion.</Char></Linea><Linea><Char>Og når nu vi kan se, at elpriserne også følger udviklingen for gas, er det interessant, i forhold til at vi nu har en situation, hvor vi sådan set har gjort os mere afhængige af udenlandsk brændstof end af dansk brændstof, fordi vi hurtigere udfaser den danske gasproduktion.</Char></Linea><Linea><Char>Og der vil jeg bare gerne høre, om Enhedslisten fortryder den disposition, som jo så medfører, at der bl.a.</Char></Linea><Linea><Char>er et øget pres på de danske elpriser.</Char></Linea></Exitus></TekstGruppe></TaleSegment></Tale><Tale><Taler><MetaSpeakerMP tingdokID="102178"><OratorFirstName>Henrik Dam</OratorFirstName><OratorLastName>Kristensen</OratorLastName><GroupNameShort>S</GroupNameShort><OratorRole>formand</OratorRole></MetaSpeakerMP><TalerTitel><Linea><Char formaChar="Bold">Formanden</Char><Char /></Linea></TalerTitel></Taler><TaleSegment><MetaSpeechSegment><LastModified>2023-08-29T16:00:05</LastModified><EdixiStatus>Typeset</EdixiStatus><StartDateTime>2022-09-08T09:11:21</StartDateTime><EndDateTime>2022-09-08T09:11:24</EndDateTime></MetaSpeechSegment><TekstGruppe><Exitus><Linea><Char>Ordføreren.</Char></Linea></Exitus></TekstGruppe></TaleSegment></Tale><Tale><Taler><MetaSpeakerMP tingdokID="103836"><OratorFirstName>Søren Egge</OratorFirstName><OratorLastName>Rasmussen</OratorLastName><GroupNameShort>EL</GroupNameShort><OratorRole>medlem</OratorRole></MetaSpeakerMP><TalerTitel><Linea><Char formaChar="Bold">Søren Egge Rasmussen</Char><Char> (EL)</Char></Linea></TalerTitel></Taler><TaleSegment><MetaSpeechSegment><LastModified>2023-08-29T16:00:05</LastModified><EdixiStatus>Typeset</EdixiStatus><StartDateTime>2022-09-08T09:11:24</StartDateTime><EndDateTime>2022-09-08T09:11:34</EndDateTime></MetaSpeechSegment><TekstGruppe><Exitus><Linea><Char>Nu er det ikke alle partier, der er med i Nordsøaftalen.</Char></Linea><Linea><Char>Bl.a.</Char></Linea><Linea><Char>er Enhedslisten ikke med i den, så det er lidt svært at svare på det spørgsmål.</Char></Linea></Exitus></TekstGruppe></TaleSegment></Tale><Tale><Taler><MetaSpeakerMP tingdokID="102178"><OratorFirstName>Henrik Dam</OratorFirstName><OratorLastName>Kristensen</OratorLastName><GroupNameShort>S</GroupNameShort><OratorRole>formand</OratorRole></MetaSpeakerMP><TalerTitel><Linea><Char formaChar="Bold">Formanden</Char><Char /></Linea></TalerTitel></Taler><TaleSegment><MetaSpeechSegment><LastModified>2023-08-29T16:00:05</LastModified><EdixiStatus>Typeset</EdixiStatus><StartDateTime>2022-09-08T09:11:34</StartDateTime><EndDateTime>2022-09-08T09:11:35</EndDateTime></MetaSpeechSegment><TekstGruppe><Exitus><Linea><Char>Hans Kristian Skibby.</Char></Linea></Exitus></TekstGruppe></TaleSegment></Tale><Tale><Taler><MetaSpeakerMP tingdokID="102295"><OratorFirstName>Hans Kristian</OratorFirstName><OratorLastName>Skibby</OratorLastName><GroupNameShort>DD</GroupNameShort><OratorRole>medlem</OratorRole></MetaSpeakerMP><TalerTitel><Linea><Char formaChar="Bold">Hans Kristian Skibby</Char><Char> (DD)</Char></Linea></TalerTitel></Taler><TaleSegment><MetaSpeechSegment><LastModified>2023-08-29T16:00:05</LastModified><EdixiStatus>Typeset</EdixiStatus><StartDateTime>2022-09-08T09:11:35</StartDateTime><EndDateTime>2022-09-08T09:11:57</EndDateTime></MetaSpeechSegment><TekstGruppe><Exitus><Linea><Char>Det ved jeg ikke om det er, for hvis man er med i en aftale, har man mulighed for at søge indflydelse på, hvad aftalen indeholder, og det er jo velkendt, at de venstreorienterede partier lagde sådan et vist pres på den regering, som stod for at forhandle det på plads.</Char></Linea><Linea><Char>Og derfor er det jo interessant at vide, om Enhedslisten kunne have set sig som en del af en anden aftalemodel.</Char></Linea></Exitus></TekstGruppe></TaleSegment></Tale><Tale><Taler><MetaSpeakerMP tingdokID="102178"><OratorFirstName>Henrik Dam</OratorFirstName><OratorLastName>Kristensen</OratorLastName><GroupNameShort>S</GroupNameShort><OratorRole>formand</OratorRole></MetaSpeakerMP><TalerTitel><Linea><Char formaChar="Bold">Formanden</Char><Char /></Linea></TalerTitel></Taler><TaleSegment><MetaSpeechSegment><LastModified>2023-08-29T16:00:05</LastModified><EdixiStatus>Typeset</EdixiStatus><StartDateTime>2022-09-08T09:11:57</StartDateTime><EndDateTime>2022-09-08T09:12:00</EndDateTime></MetaSpeechSegment><TekstGruppe><Exitus><Linea><Char>Ordføreren.</Char></Linea></Exitus></TekstGruppe></TaleSegment></Tale><Tale><Taler><MetaSpeakerMP tingdokID="103836"><OratorFirstName>Søren Egge</OratorFirstName><OratorLastName>Rasmussen</OratorLastName><GroupNameShort>EL</GroupNameShort><OratorRole>medlem</OratorRole></MetaSpeakerMP><TalerTitel><Linea><Char formaChar="Bold">Søren Egge Rasmussen</Char><Char> (EL)</Char></Linea></TalerTitel></Taler><TaleSegment><MetaSpeechSegment><LastModified>2023-08-29T16:00:05</LastModified><EdixiStatus>Typeset</EdixiStatus><StartDateTime>2022-09-08T09:12:00</StartDateTime><EndDateTime>2022-09-08T09:12:21</EndDateTime></MetaSpeechSegment><TekstGruppe><Exitus><Linea><Char>Jamen jeg vil gerne gentage:</Char></Linea><Linea><Char>Vi er ikke med i Nordsøaftalen, så derfor ved jeg jo ikke, hvad der er blevet forhandlet om i Nordsøaftalen.</Char></Linea><Linea><Char>Jeg ved ikke, om man kan høre det helt nede næstbagerst i salen:</Char></Linea><Linea><Char>Enhedslisten er ikke med i Nordsøaftalen.</Char></Linea><Linea><Char>Vi laver meget gerne fremtidsrettede aftaler for Nordsøen, og det er jo det, vi har gjort ved at arbejde for den her energiø og rigtig mange havvindmøller ude i Nordsøen; det er sådan set fremtidens energiforsyning i Nordsøen.</Char></Linea></Exitus></TekstGruppe></TaleSegment></Tale><Tale><Taler><MetaSpeakerMP tingdokID="102178"><OratorFirstName>Henrik Dam</OratorFirstName><OratorLastName>Kristensen</OratorLastName><GroupNameShort>S</GroupNameShort><OratorRole>formand</OratorRole></MetaSpeakerMP><TalerTitel><Linea><Char formaChar="Bold">Formanden</Char><Char /></Linea></TalerTitel></Taler><TaleSegment><MetaSpeechSegment><LastModified>2023-08-29T16:00:05</LastModified><EdixiStatus>Typeset</EdixiStatus><StartDateTime>2022-09-08T09:12:21</StartDateTime><EndDateTime>2022-09-08T09:12:29</EndDateTime></MetaSpeechSegment><TekstGruppe><Exitus><Linea><Char>Hr.</Char></Linea><Linea><Char>Bent Bøgsted, Danmarksdemokraterne.</Char></Linea></Exitus></TekstGruppe></TaleSegment></Tale><Tale><Taler><MetaSpeakerMP tingdokID="100581"><OratorFirstName>Bent</OratorFirstName><OratorLastName>Bøgsted</OratorLastName><GroupNameShort>DD</GroupNameShort><OratorRole>medlem</OratorRole></MetaSpeakerMP><TalerTitel><Linea><Char formaChar="Bold">Bent Bøgsted</Char><Char> (DD)</Char></Linea></TalerTitel></Taler><TaleSegment><MetaSpeechSegment><LastModified>2023-08-29T16:00:05</LastModified><EdixiStatus>Typeset</EdixiStatus><StartDateTime>2022-09-08T09:12:29</StartDateTime><EndDateTime>2022-09-08T09:12:56</EndDateTime></MetaSpeechSegment><TekstGruppe><Exitus><Linea><Char>Vi kan sagtens høre hernede fra den bageste række, og jeg håber også, at ordføreren kan høre mig fra talerstolen.</Char></Linea><Linea><Char>Jeg vil gerne spørge ordføreren:</Char></Linea><Linea><Char>Mener Enhedslisten, at gasproduktionen i Danmark skal øges, eller vil Enhedslisten have lukket totalt for gasproduktionen i Danmark?</Char></Linea><Linea><Char>Nu kommer Tyrafeltet jo op at køre om et år, hvor gassen skal produceres.</Char></Linea><Linea><Char>Vil Enhedslisten have, at gasproduktionen skal øges, så vi kan modvirke det problem, vi har nu, med stigende gaspriser?</Char></Linea></Exitus></TekstGruppe></TaleSegment></Tale><Tale><Taler><MetaSpeakerMP tingdokID="102178"><OratorFirstName>Henrik Dam</OratorFirstName><OratorLastName>Kristensen</OratorLastName><GroupNameShort>S</GroupNameShort><OratorRole>formand</OratorRole></MetaSpeakerMP><TalerTitel><Linea><Char formaChar="Bold">Formanden</Char><Char /></Linea></TalerTitel></Taler><TaleSegment><MetaSpeechSegment><LastModified>2023-08-29T16:00:05</LastModified><EdixiStatus>Typeset</EdixiStatus><StartDateTime>2022-09-08T09:12:56</StartDateTime><EndDateTime>2022-09-08T09:12:59</EndDateTime></MetaSpeechSegment><TekstGruppe><Exitus><Linea><Char>Ordføreren.</Char></Linea></Exitus></TekstGruppe></TaleSegment></Tale><Tale><Taler><MetaSpeakerMP tingdokID="103836"><OratorFirstName>Søren Egge</OratorFirstName><OratorLastName>Rasmussen</OratorLastName><GroupNameShort>EL</GroupNameShort><OratorRole>medlem</OratorRole></MetaSpeakerMP><TalerTitel><Linea><Char formaChar="Bold">Søren Egge Rasmussen</Char><Char> (EL)</Char></Linea></TalerTitel></Taler><TaleSegment><MetaSpeechSegment><LastModified>2023-08-29T16:00:05</LastModified><EdixiStatus>Typeset</EdixiStatus><StartDateTime>2022-09-08T09:12:59</StartDateTime><EndDateTime>2022-09-08T09:13:20</EndDateTime></MetaSpeechSegment><TekstGruppe><Exitus><Linea><Char>Nej, det er ikke vores politik at øge den fossile gasindvinding.</Char></Linea><Linea><Char>Det er meget klart.</Char></Linea><Linea><Char>Vi vil nok heller ikke blive inviteret til de forhandlinger, fordi vi – som det kan høres nede på næstsidste række – ikke er med i Nordsøaftalen.</Char></Linea><Linea><Char>Så det er sådan set der, hvor vi står.</Char></Linea><Linea><Char>Det, vi vil satse på, er sådan set udviklingen af den vedvarende energi, og der er vi med i rigtig mange aftaler, som håndterer det på fortræffelig vis.</Char></Linea></Exitus></TekstGruppe></TaleSegment></Tale><Tale><Taler><MetaSpeakerMP tingdokID="102178"><OratorFirstName>Henrik Dam</OratorFirstName><OratorLastName>Kristensen</OratorLastName><GroupNameShort>S</GroupNameShort><OratorRole>formand</OratorRole></MetaSpeakerMP><TalerTitel><Linea><Char formaChar="Bold">Formanden</Char><Char /></Linea></TalerTitel></Taler><TaleSegment><MetaSpeechSegment><LastModified>2023-08-29T16:00:05</LastModified><EdixiStatus>Typeset</EdixiStatus><StartDateTime>2022-09-08T09:13:20</StartDateTime><EndDateTime>2022-09-08T09:13:23</EndDateTime></MetaSpeechSegment><TekstGruppe><Exitus><Linea><Char>Bent Bøgsted.</Char></Linea></Exitus></TekstGruppe></TaleSegment></Tale><Tale><Taler><MetaSpeakerMP tingdokID="100581"><OratorFirstName>Bent</OratorFirstName><OratorLastName>Bøgsted</OratorLastName><GroupNameShort>DD</GroupNameShort><OratorRole>medlem</OratorRole></MetaSpeakerMP><TalerTitel><Linea><Char formaChar="Bold">Bent Bøgsted</Char><Char> (DD)</Char></Linea></TalerTitel></Taler><TaleSegment><MetaSpeechSegment><LastModified>2023-08-29T16:00:05</LastModified><EdixiStatus>Typeset</EdixiStatus><StartDateTime>2022-09-08T09:13:23</StartDateTime><EndDateTime>2022-09-08T09:13:43</EndDateTime></MetaSpeechSegment><TekstGruppe><Exitus><Linea><Char>Det vil jo så sige, at jeg kan forstå det sådan, at Enhedslisten, når man ikke er med i Nordsøaftalen, ikke har nogen holdning til, om Danmark skal øge gasproduktionen.</Char></Linea><Linea><Char>Jeg kan forstå det sådan, at Enhedslisten vil have det totalt udfaset, og de vil have, at vi skal have stigende priser, fordi vi ikke selv kan producere gas.</Char></Linea><Linea><Char>Det er sådan, jeg kan tolke det.</Char></Linea></Exitus></TekstGruppe></TaleSegment></Tale><Tale><Taler><MetaSpeakerMP tingdokID="102178"><OratorFirstName>Henrik Dam</OratorFirstName><OratorLastName>Kristensen</OratorLastName><GroupNameShort>S</GroupNameShort><OratorRole>formand</OratorRole></MetaSpeakerMP><TalerTitel><Linea><Char formaChar="Bold">Formanden</Char><Char /></Linea></TalerTitel></Taler><TaleSegment><MetaSpeechSegment><LastModified>2023-08-29T16:00:05</LastModified><EdixiStatus>Typeset</EdixiStatus><StartDateTime>2022-09-08T09:13:43</StartDateTime><EndDateTime>2022-09-08T09:13:46</EndDateTime></MetaSpeechSegment><TekstGruppe><Exitus><Linea><Char>Ordføreren.</Char></Linea></Exitus></TekstGruppe></TaleSegment></Tale><Tale><Taler><MetaSpeakerMP tingdokID="103836"><OratorFirstName>Søren Egge</OratorFirstName><OratorLastName>Rasmussen</OratorLastName><GroupNameShort>EL</GroupNameShort><OratorRole>medlem</OratorRole></MetaSpeakerMP><TalerTitel><Linea><Char formaChar="Bold">Søren Egge Rasmussen</Char><Char> (EL)</Char></Linea></TalerTitel></Taler><TaleSegment><MetaSpeechSegment><LastModified>2023-08-29T16:00:05</LastModified><EdixiStatus>Typeset</EdixiStatus><StartDateTime>2022-09-08T09:13:46</StartDateTime><EndDateTime>2022-09-08T09:14:12</EndDateTime></MetaSpeechSegment><TekstGruppe><Exitus><Linea><Char>Det er klart, at med de klimaproblemer, vi står i, skal vi udfase anvendelsen af fossil gas.</Char></Linea><Linea><Char>Det er sådan set det, vi står over for.</Char></Linea><Linea><Char>Hvor hurtigt det kan ske, kan der være forskellige holdninger til, men vi er nødt til det af klimamæssige årsager.</Char></Linea><Linea><Char>Vi er så også nødt til at lade nogle af de fossile reserver, som er kendte, blive i undergrunden, for at vi kan sikre, at temperaturstigningen holdes under 2 grader.</Char></Linea><Linea><Char>Så der er en vis sammenhæng i tingene.</Char></Linea></Exitus></TekstGruppe></TaleSegment></Tale><Tale><Taler><MetaSpeakerMP tingdokID="102178"><OratorFirstName>Henrik Dam</OratorFirstName><OratorLastName>Kristensen</OratorLastName><GroupNameShort>S</GroupNameShort><OratorRole>formand</OratorRole></MetaSpeakerMP><TalerTitel><Linea><Char formaChar="Bold">Formanden</Char><Char /></Linea></TalerTitel></Taler><TaleSegment><MetaSpeechSegment><LastModified>2023-08-29T16:00:05</LastModified><EdixiStatus>Typeset</EdixiStatus><StartDateTime>2022-09-08T09:14:12</StartDateTime><EndDateTime>2022-09-08T09:14:35</EndDateTime></MetaSpeechSegment><TekstGruppe><Exitus><Linea><Char>Tak til ordføreren.</Char></Linea><Linea><Char>Der er ikke flere korte bemærkninger.</Char></Linea></Exitus><Exitus formaForma="NormalInd"><Linea><Char>Er der flere, der ønsker at udtale sig?</Char></Linea></Exitus><Exitus formaForma="NormalInd"><Linea><Char>Da det ikke er tilfældet, er forhandlingen sluttet.</Char></Linea></Exitus></TekstGruppe><TekstGruppe><Exitus formaForma="NormalLuft"><Linea><Char>Jeg foreslår, at lovforslaget går direkte til tredje behandling uden fornyet udvalgsbehandling.</Char></Linea><Linea><Char>Og hvis ingen gør indsigelse, betragter jeg det som vedtaget.</Char></Linea></Exitus><Exitus formaForma="NormalInd"><Linea><Char>Det er vedtaget.</Char></Linea></Exitus></TekstGruppe></TaleSegment></Tale></Aktivitet></DagsordenPunkt><DagsordenPunkt><MetaFTAgendaItem><ItemNo>2</ItemNo><FTCase tingdokID="579606" /><FTCaseNumber>205</FTCaseNumber><FTCaseType>L</FTCaseType><FTCaseStage>BEH2</FTCaseStage><ShortTitle>2. behandling af L 205: Om fremrykning af forhøjelse af SU-fribeløb.</ShortTitle></MetaFTAgendaItem><PunktTekst><PreTekst><Exitus><Linea><Char>Det næste punkt på dagsordenen er:</Char></Linea></Exitus></PreTekst><Exitus><Linea><Char formaChar="Bold">2) 2. behandling af lovforslag nr. L 205:</Char></Linea></Exitus><Exitus><Linea><Char formaChar="Bold">Forslag til lov om ændring af lov om ændring af SU-loven. (Fremrykning af forhøjelse af SU-fribeløb).</Char></Linea></Exitus><Exitus><Linea><Char>Af uddannelses- og forskningsministeren (Jesper Petersen).</Char></Linea></Exitus><Exitus><Linea><Char>(Fremsættelse 23.08.2022. 1. behandling 25.08.2022. Betænkning 30.08.2022).</Char></Linea></Exitus></PunktTekst><Aktivitet><Rubrica><Linea><Char>Forhandling</Char></Linea></Rubrica><Tale><Taler><MetaSpeakerMP tingdokID="102178"><OratorFirstName>Henrik Dam</OratorFirstName><OratorLastName>Kristensen</OratorLastName><GroupNameShort>S</GroupNameShort><OratorRole>formand</OratorRole></MetaSpeakerMP><TalerTitel><Linea><Char formaChar="Bold">Formanden</Char><Char /></Linea></TalerTitel></Taler><TaleSegment><MetaSpeechSegment><LastModified>2023-08-29T16:00:05</LastModified><EdixiStatus>Typeset</EdixiStatus><StartDateTime>2022-09-08T09:14:35</StartDateTime><EndDateTime>2022-09-08T09:14:47</EndDateTime></MetaSpeechSegment><TekstGruppe><Exitus><Linea><Char>Der er stillet ændringsforslag.</Char></Linea></Exitus><Exitus formaForma="NormalInd"><Linea><Char>Er der nogen, der ønsker at udtale sig?</Char></Linea></Exitus><Exitus formaForma="NormalInd"><Linea><Char>Da det ikke er tilfældet, er forhandlingen slut, og vi går til afstemning.</Char></Linea></Exitus></TekstGruppe></TaleSegment></Tale></Aktivitet><Aktivitet><Rubrica><Linea><Char>Afstemning</Char></Linea></Rubrica><Tale><Taler><MetaSpeakerMP tingdokID="102178"><OratorFirstName>Henrik Dam</OratorFirstName><OratorLastName>Kristensen</OratorLastName><GroupNameShort>S</GroupNameShort><OratorRole>formand</OratorRole></MetaSpeakerMP><TalerTitel><Linea><Char formaChar="Bold">Formanden</Char><Char /></Linea></TalerTitel></Taler><TaleSegment><MetaSpeechSegment><LastModified>2023-08-29T16:00:05</LastModified><EdixiStatus>Typeset</EdixiStatus><StartDateTime>2022-09-08T09:14:47</StartDateTime><EndDateTime>2022-09-08T09:15:46</EndDateTime></MetaSpeechSegment><TekstGruppe><Exitus><Linea><Char>Der stemmes om ændringsforslag nr.</Char></Linea><Linea><Char>2 af et mindretal (DD), tiltrådt af et mindretal (DF, NB, LA og Marie Krarup (UFG)), og der kan stemmes.</Char></Linea></Exitus><Exitus formaForma="NormalInd"><Linea><Char>Jah, er man klar over, hvad man vil stemme?</Char></Linea><Linea><Char>Godt.</Char></Linea></Exitus><Exitus formaForma="NormalInd"><Linea><Char>Afstemningen slutter.</Char></Linea></Exitus></TekstGruppe><TekstGruppe><Exitus formaForma="NormalLuft"><Linea><Char>For stemte 22 (KF (ved en fejl), DD, DF, NB, LA og Liselott Blixt (UFG)), imod stemte 77 (S, V, SF, RV, EL og FG), hverken for eller imod stemte 0.</Char></Linea></Exitus></TekstGruppe><TekstGruppe><Exitus formaForma="NormalLuft"><Linea><Char>Ændringsforslaget er forkastet.</Char></Linea></Exitus></TekstGruppe><TekstGruppe><Exitus formaForma="NormalLuft"><Linea><Char>Herefter er ændringsforslag nr.</Char></Linea><Linea><Char>1 og 3, stillet og tiltrådt af de samme mindretal, bortfaldet.</Char></Linea></Exitus></TekstGruppe><TekstGruppe><Exitus formaForma="NormalLuft"><Linea><Char>Jeg foreslår, at lovforslaget går direkte til tredje behandling uden fornyet udvalgsbehandling, og hvis ingen gør indsigelse, betragter jeg det som vedtaget.</Char></Linea></Exitus><Exitus formaForma="NormalInd"><Linea><Char>Det er vedtaget.</Char></Linea></Exitus></TekstGruppe></TaleSegment></Tale></Aktivitet></DagsordenPunkt><DagsordenPunkt><MetaFTAgendaItem><ItemNo>3</ItemNo><FTCase tingdokID="579607" /><FTCaseNumber>206</FTCaseNumber><FTCaseType>L</FTCaseType><FTCaseStage>BEH2</FTCaseStage><ShortTitle>2. behandling af L 206: Om ekstra økonomisk støtte til modtagere af ældrechecken, overførselsmodtagere, SU-handicaptillægsmodtag</ShortTitle></MetaFTAgendaItem><PunktTekst><PreTekst><Exitus><Linea><Char>Det sidste punkt på dagsordenen er:</Char></Linea></Exitus></PreTekst><Exitus><Linea><Char formaChar="Bold">3) 2. behandling af lovforslag nr. L 206:</Char></Linea></Exitus><Exitus><Linea><Char formaChar="Bold">Forslag til lov om en ekstra økonomisk støtte til modtagere af ældrechecken, engangsbeløb til overførselsmodtagere, der har trukket sig tilbage fra arbejdsmarkedet, og engangsbeløb til uddannelsessøgende, der modtager stipendium som tillæg på grund af en funktionsnedsættelse eller som enlige forsørgere.

</Char></Linea></Exitus><Exitus><Linea><Char>Af beskæftigelsesministeren (Peter Hummelgaard).</Char></Linea></Exitus><Exitus><Linea><Char>(Fremsættelse 23.08.2022. 1. behandling 25.08.2022. Betænkning 01.09.2022).</Char></Linea></Exitus></PunktTekst><Aktivitet><Rubrica><Linea><Char>Forhandling</Char></Linea></Rubrica><Tale><Taler><MetaSpeakerMP tingdokID="102178"><OratorFirstName>Henrik Dam</OratorFirstName><OratorLastName>Kristensen</OratorLastName><GroupNameShort>S</GroupNameShort><OratorRole>formand</OratorRole></MetaSpeakerMP><TalerTitel><Linea><Char formaChar="Bold">Formanden</Char><Char /></Linea></TalerTitel></Taler><TaleSegment><MetaSpeechSegment><LastModified>2023-08-29T16:00:05</LastModified><EdixiStatus>Typeset</EdixiStatus><StartDateTime>2022-09-08T09:15:46</StartDateTime><EndDateTime>2022-09-08T09:16:10</EndDateTime></MetaSpeechSegment><TekstGruppe><Exitus><Linea><Char>Der er stillet ændringsforslag.</Char></Linea></Exitus><Exitus formaForma="NormalInd"><Linea><Char> Er der nogen, der ønsker at udtale sig?</Char></Linea></Exitus><Exitus formaForma="NormalInd"><Linea><Char>Da det ikke er tilfældet, er forhandlingen sluttet, og vi går til afstemning.</Char></Linea></Exitus></TekstGruppe></TaleSegment></Tale></Aktivitet><Aktivitet><Rubrica><Linea><Char>Afstemning</Char></Linea></Rubrica><Tale><Taler><MetaSpeakerMP tingdokID="102178"><OratorFirstName>Henrik Dam</OratorFirstName><OratorLastName>Kristensen</OratorLastName><GroupNameShort>S</GroupNameShort><OratorRole>formand</OratorRole></MetaSpeakerMP><TalerTitel><Linea><Char formaChar="Bold">Formanden</Char><Char /></Linea></TalerTitel></Taler><TaleSegment><MetaSpeechSegment><LastModified>2023-08-29T16:00:05</LastModified><EdixiStatus>Typeset</EdixiStatus><StartDateTime>2022-09-08T09:16:10</StartDateTime><EndDateTime>2022-09-08T09:16:23</EndDateTime></MetaSpeechSegment><TekstGruppe><Exitus><Linea><Char>Ønskes afstemning om ændringsforslag nr.</Char></Linea><Linea><Char>1, tiltrådt af et flertal (udvalget med undtagelse af KF, DF og NB)?</Char></Linea></Exitus><Exitus formaForma="NormalInd"><Linea><Char>Det er vedtaget.</Char></Linea></Exitus></TekstGruppe><TekstGruppe><Exitus formaForma="NormalLuft"><Linea><Char>Jeg foreslår, at lovforslaget går direkte til tredje behandling uden fornyet udvalgsbehandling, og hvis ingen gør indsigelse, betragter jeg det som vedtaget.</Char></Linea></Exitus><Exitus formaForma="NormalInd"><Linea><Char>Det er vedtaget.</Char></Linea></Exitus></TekstGruppe></TaleSegment></Tale></Aktivitet></DagsordenPunkt><DagsordenPunkt><MetaFTAgendaItem><ItemNo>0</ItemNo><FTCase /><FTCaseNumber /><FTCaseType>FM</FTCaseType><FTCaseStage /><ShortTitle>Punkt 0</ShortTitle></MetaFTAgendaItem><PunktTekst><Exitus><Linea><Char /></Linea></Exitus></PunktTekst><Aktivitet><Rubrica><Linea><Char>Meddelelser fra formanden</Char></Linea></Rubrica><Tale><Taler><MetaSpeakerMP tingdokID="102178"><OratorFirstName>Henrik Dam</OratorFirstName><OratorLastName>Kristensen</OratorLastName><GroupNameShort>S</GroupNameShort><OratorRole>formand</OratorRole></MetaSpeakerMP><TalerTitel><Linea><Char formaChar="Bold">Formanden</Char><Char /></Linea></TalerTitel></Taler><TaleSegment><MetaSpeechSegment><LastModified>2023-08-29T16:00:05</LastModified><EdixiStatus>Typeset</EdixiStatus><StartDateTime>2022-09-08T09:16:23</StartDateTime><EndDateTime>2022-09-08T09:16:42</EndDateTime></MetaSpeechSegment><TekstGruppe><Exitus><Linea><Char>Det var så det sidste, der var at foretage i dette møde, men dagen er jo ikke færdig endnu.</Char></Linea><Linea><Char>Men af tekniske årsager er vi nødt til at holde en kort pause.</Char></Linea></Exitus></TekstGruppe><TekstGruppe><Exitus formaForma="NormalLuft"><Linea><Char>Folketingets næste møde afholdes i dag, kl.</Char></Linea><Linea><Char>9.25.</Char></Linea></Exitus><Exitus formaForma="NormalInd"><Linea><Char>Jeg henviser til den dagsorden, der fremgår af Folketingets hjemmeside.</Char></Linea></Exitus></TekstGruppe></TaleSegment></Tale></Aktivitet><Aktivitet><Tale><Taler><MetaSpeakerMP tingdokID=""><OratorFirstName>MødeSlut</OratorFirstName><OratorLastName>MødeSlut</OratorLastName><GroupNameShort>MødeSlut</GroupNameShort><OratorRole>MødeSlut</OratorRole></MetaSpeakerMP><TalerTitel><Linea><Char formaChar="Bold" /><Char /></Linea></TalerTitel></Taler><TaleSegment><MetaSpeechSegment><LastModified>2023-08-29T16:00:05</LastModified><EdixiStatus>Typeset</EdixiStatus><StartDateTime>2022-09-08T09:16:42</StartDateTime></MetaSpeechSegment><TekstGruppe><Exitus><Linea><Char>Mødet er hævet.</Char></Linea><Linea><Char>(Kl.</Char></Linea><Linea><Char>09:16).</Char></Linea></Exitus></TekstGruppe></TaleSegment></Tale></Aktivitet></DagsordenPunkt></Dokument>